replit2/__init__.py
replit2/__main__.py
replit2/audio/Makefile
replit2/audio/__init__.py
replit2/audio/test.py
replit2/audio/types.py
replit2/database/__init__.py
replit2/database/database.py
replit2/database/default_db.py
replit2/database/server.py
replit2/goval/__init__.py
replit2/goval/api/__init__.py
replit2/goval/api/client_pb2.py
replit2/goval/api/features/__init__.py
replit2/goval/api/features/features_pb2.py
replit2/goval/api/repl/__init__.py
replit2/goval/api/repl/repl_pb2.py
replit2/goval/api/signing_pb2.py
replit2/identity/__init__.py
replit2/identity/exceptions.py
replit2/identity/verify.py
replit2/info.py
replit2/web/__init__.py
replit2/web/app.py
replit2/web/user.py
replit2/web/utils.py
replit2-3.3.0.dist-info/LICENSE
replit2-3.3.0.dist-info/METADATA
replit2-3.3.0.dist-info/WHEEL
replit2-3.3.0.dist-info/entry_points.txt
replit2-3.3.0.dist-info/RECORD
