Metadata-Version: 2.1
Name: replit2
Version: 3.3.0
Summary: A library for interacting with features of repl.it
Home-page: https://github.com/py660/repl.it
License: ISC
Author: Repl.it
Author-email: contact@repl.it
Requires-Python: >=3.8,<4.0
Classifier: License :: OSI Approved
Classifier: Programming Language :: Python :: 3
Classifier: Programming Language :: Python :: 3.8
Classifier: Programming Language :: Python :: 3.9
Classifier: Programming Language :: Python :: 3.10
Classifier: Programming Language :: Python :: 3.11
Requires-Dist: Flask (>=2.0.0,<3.0.0)
Requires-Dist: Werkzeug (>=2.0.0,<3.0.0)
Requires-Dist: aiohttp (>=3.6.2,<4.0.0)
Requires-Dist: protobuf (>=4.21.8,<5.0.0)
Requires-Dist: pyseto (>=1.6.11,<2.0.0)
Requires-Dist: requests (>=2.25.1,<3.0.0)
Requires-Dist: typing_extensions (>=3.7.4,<4.0.0)
Project-URL: Documentation, https://replit-py.readthedocs.org/
Project-URL: Repository, https://github.com/py660/repl.it
